tool_detector/__init__.py
tool_detector/cli.py
tool_detector/decorator.py
tool_detector/detector.py
tool_detector/types.py
tool_detector-0.1.0.dist-info/METADATA
tool_detector-0.1.0.dist-info/WHEEL
tool_detector-0.1.0.dist-info/entry_points.txt
tool_detector-0.1.0.dist-info/licenses/LICENSE
tool_detector-0.1.0.dist-info/RECORD
