Metadata-Version: 2.4
Name: tool-detector
Version: 0.1.0
Summary: A lightweight tool detection system for parsing user intents into structured tool calls
Project-URL: Homepage, https://github.com/ameenalam/tool-detector
Project-URL: Documentation, https://tool-detector.readthedocs.io/
Project-URL: Repository, https://github.com/ameenalam/tool-detector.git
Project-URL: Bug Tracker, https://github.com/ameenalam/tool-detector/issues
Project-URL: Changelog, https://github.com/ameenalam/tool-detector/blob/main/CHANGELOG.md
Author-email: Ameen Alam <ameen@doblier.io>
Maintainer-email: Ameen Alam <ameen@doblier.io>
License: MIT
License-File: LICENSE
Keywords: ai,intent-parsing,natural-language-processing,nlp,tool-detection
Classifier: Development Status :: 4 - Beta
Classifier: Intended Audience :: Developers
Classifier: License :: OSI Approved :: MIT License
Classifier: Operating System :: OS Independent
Classifier: Programming Language :: Python :: 3
Classifier: Programming Language :: Python :: 3.8
Classifier: Programming Language :: Python :: 3.9
Classifier: Programming Language :: Python :: 3.10
Classifier: Programming Language :: Python :: 3.11
Classifier: Programming Language :: Python :: 3.12
Classifier: Topic :: Scientific/Engineering :: Artificial Intelligence
Classifier: Topic :: Software Development :: Libraries :: Python Modules
Classifier: Topic :: Text Processing :: Linguistic
Requires-Python: >=3.8
Requires-Dist: pydantic>=2.0.0
Provides-Extra: dev
Requires-Dist: black>=23.0; extra == 'dev'
Requires-Dist: flake8>=6.0; extra == 'dev'
Requires-Dist: isort>=5.0; extra == 'dev'
Requires-Dist: mypy>=1.0; extra == 'dev'
Requires-Dist: pre-commit>=3.0; extra == 'dev'
Requires-Dist: pytest-cov>=4.0; extra == 'dev'
Requires-Dist: pytest>=7.0; extra == 'dev'
Provides-Extra: docs
Requires-Dist: myst-parser>=1.0; extra == 'docs'
Requires-Dist: sphinx-rtd-theme>=1.0; extra == 'docs'
Requires-Dist: sphinx>=6.0; extra == 'docs'
